airscript/__init__.py
airscript/data.py
airscript/action/__init__.py
airscript/action/gesture.py
airscript/action/key.py
airscript/action/path.py
airscript/action/touch.py
airscript/graphics/__init__.py
airscript/intent/__init__.py
airscript/node/__init__.py
airscript/node/node.py
airscript/screen/__init__.py
airscript/system/Prgogress.py
airscript/system/__init__.py
airscript/ui/__init__.py
airscript/ui/dialog.py
as_android-0.0.7.dist-info/METADATA
as_android-0.0.7.dist-info/WHEEL
as_android-0.0.7.dist-info/top_level.txt
as_android-0.0.7.dist-info/RECORD
